{
  "ontology": {
    "name": "communication_ontology",
    "version": "2.0.0",
    "namespace": "http://context-machine.org/ontology/communication#",
    "description": "Comprehensive ontology for modern communication systems, digital media, telecommunications infrastructure, social networks, content management, broadcasting, and information dissemination across all channels and platforms.",
    "namespaces": {
      "comm": "http://context-machine.org/ontology/communication#",
      "telecom": "http://context-machine.org/ontology/communication/telecom#",
      "media": "http://context-machine.org/ontology/communication/media#",
      "social": "http://context-machine.org/ontology/communication/social#",
      "broadcast": "http://context-machine.org/ontology/communication/broadcast#",
      "digital": "http://context-machine.org/ontology/communication/digital#",
      "mobile": "http://context-machine.org/ontology/communication/mobile#",
      "internet": "http://context-machine.org/ontology/communication/internet#",
      "messaging": "http://context-machine.org/ontology/communication/messaging#",
      "voice": "http://context-machine.org/ontology/communication/voice#",
      "video": "http://context-machine.org/ontology/communication/video#",
      "content": "http://context-machine.org/ontology/communication/content#",
      "network": "http://context-machine.org/ontology/communication/network#",
      "protocol": "http://context-machine.org/ontology/communication/protocol#",
      "security": "http://context-machine.org/ontology/communication/security#",
      "analytics": "http://context-machine.org/ontology/communication/analytics#",
      "marketing": "http://context-machine.org/ontology/communication/marketing#",
      "journalism": "http://context-machine.org/ontology/communication/journalism#",
      "pr": "http://context-machine.org/ontology/communication/pr#",
      "advertising": "http://context-machine.org/ontology/communication/advertising#",
      "streaming": "http://context-machine.org/ontology/communication/streaming#",
      "satellite": "http://context-machine.org/ontology/communication/satellite#",
      "emergency": "http://context-machine.org/ontology/communication/emergency#"
    },
    "imports": [
      "http://context-machine.org/ontology/universal#",
      "http://www.w3.org/2006/time#",
      "http://www.opengis.net/ont/geosparql#",
      "http://qudt.org/vocab/unit#",
      "http://purl.org/dc/elements/1.1/",
      "http://xmlns.com/foaf/0.1/",
      "http://www.w3.org/ns/prov#"
    ],

    "frames": {
      "Telecommunications_Infrastructure": {
        "collections": {
          "Network_Architecture": {
            "entities": {
              "TelecomNetwork": {
                "properties": {
                  "network_id": "xsd:string",
                  "network_name": "xsd:string",
                  "network_type": "xsd:string",
                  "network_topology": "xsd:string",
                  "coverage_area": "geo:Polygon",
                  "service_provider": "xsd:string",
                  "technology_standard": "xsd:string",
                  "frequency_bands": "xsd:string",
                  "bandwidth_capacity": "xsd:float",
                  "data_rate_mbps": "xsd:float",
                  "latency_ms": "xsd:float",
                  "reliability_percentage": "xsd:float",
                  "availability_sla": "xsd:float",
                  "subscriber_count": "xsd:integer",
                  "concurrent_users": "xsd:integer",
                  "peak_traffic_gbps": "xsd:float",
                  "average_utilization": "xsd:float",
                  "quality_of_service": "xsd:string",
                  "security_protocols": "xsd:string",
                  "encryption_standards": "xsd:string",
                  "authentication_methods": "xsd:string",
                  "network_slicing": "xsd:boolean",
                  "edge_computing": "xsd:boolean",
                  "cdn_integration": "xsd:boolean",
                  "disaster_recovery": "xsd:string",
                  "redundancy_level": "xsd:string",
                  "maintenance_schedule": "xsd:string",
                  "upgrade_roadmap": "xsd:string",
                  "regulatory_compliance": "xsd:string",
                  "environmental_impact": "xsd:string",
                  "energy_efficiency": "xsd:float",
                  "carbon_footprint": "xsd:float"
                }
              },
              "BaseStation": {
                "properties": {
                  "station_id": "xsd:string",
                  "station_type": "xsd:string",
                  "technology": "xsd:string",
                  "location": "geo:Point",
                  "coverage_radius_km": "xsd:float",
                  "antenna_height_m": "xsd:float",
                  "antenna_type": "xsd:string",
                  "antenna_gain_dbi": "xsd:float",
                  "transmit_power_watts": "xsd:float",
                  "frequency_allocation": "xsd:string",
                  "channel_bandwidth": "xsd:float",
                  "sector_count": "xsd:integer",
                  "beam_forming": "xsd:boolean",
                  "mimo_configuration": "xsd:string",
                  "carrier_aggregation": "xsd:boolean",
                  "backhaul_type": "xsd:string",
                  "backhaul_capacity": "xsd:float",
                  "connected_users": "xsd:integer",
                  "traffic_load": "xsd:float",
                  "signal_strength_dbm": "xsd:float",
                  "interference_level": "xsd:float",
                  "handover_success_rate": "xsd:float",
                  "call_drop_rate": "xsd:float",
                  "data_throughput": "xsd:float",
                  "installation_date": "xsd:date",
                  "last_maintenance": "xsd:date",
                  "operational_status": "xsd:string",
                  "power_consumption_kw": "xsd:float",
                  "cooling_system": "xsd:string",
                  "environmental_conditions": "xsd:string"
                }
              },
              "DataCenter": {
                "properties": {
                  "datacenter_id": "xsd:string",
                  "datacenter_name": "xsd:string",
                  "location": "geo:Point",
                  "tier_classification": "xsd:string",
                  "total_capacity_mw": "xsd:float",
                  "used_capacity_mw": "xsd:float",
                  "pue_ratio": "xsd:float",
                  "cooling_efficiency": "xsd:float",
                  "server_count": "xsd:integer",
                  "storage_capacity_pb": "xsd:float",
                  "network_capacity_tbps": "xsd:float",
                  "uptime_percentage": "xsd:float",
                  "redundancy_level": "xsd:string",
                  "backup_power": "xsd:string",
                  "security_level": "xsd:string",
                  "compliance_certifications": "xsd:string",
                  "environmental_controls": "xsd:string",
                  "fire_suppression": "xsd:string",
                  "access_controls": "xsd:string",
                  "monitoring_systems": "xsd:string",
                  "maintenance_contracts": "xsd:string",
                  "disaster_recovery_site": "xsd:string",
                  "carbon_neutral": "xsd:boolean",
                  "renewable_energy_percentage": "xsd:float"
                }
              }
            }
          },
          "Communication_Protocols": {
            "entities": {
              "NetworkProtocol": {
                "properties": {
                  "protocol_id": "xsd:string",
                  "protocol_name": "xsd:string",
                  "protocol_version": "xsd:string",
                  "protocol_family": "xsd:string",
                  "osi_layer": "xsd:integer",
                  "tcp_ip_layer": "xsd:string",
                  "port_numbers": "xsd:string",
                  "header_size_bytes": "xsd:integer",
                  "payload_size_max": "xsd:integer",
                  "connection_oriented": "xsd:boolean",
                  "reliable_delivery": "xsd:boolean",
                  "flow_control": "xsd:boolean",
                  "congestion_control": "xsd:boolean",
                  "error_detection": "xsd:boolean",
                  "error_correction": "xsd:boolean",
                  "encryption_support": "xsd:boolean",
                  "authentication_support": "xsd:boolean",
                  "compression_support": "xsd:boolean",
                  "multicast_support": "xsd:boolean",
                  "qos_support": "xsd:boolean",
                  "bandwidth_efficiency": "xsd:float",
                  "latency_overhead_ms": "xsd:float",
                  "cpu_overhead": "xsd:string",
                  "memory_overhead": "xsd:string",
                  "scalability": "xsd:string",
                  "interoperability": "xsd:string",
                  "standardization_body": "xsd:string",
                  "rfc_number": "xsd:string",
                  "adoption_rate": "xsd:string",
                  "security_vulnerabilities": "xsd:string",
                  "performance_benchmarks": "xsd:string"
                }
              },
              "APIEndpoint": {
                "properties": {
                  "endpoint_id": "xsd:string",
                  "endpoint_url": "xsd:anyURI",
                  "http_method": "xsd:string",
                  "api_version": "xsd:string",
                  "authentication_type": "xsd:string",
                  "authorization_scope": "xsd:string",
                  "rate_limit": "xsd:integer",
                  "request_format": "xsd:string",
                  "response_format": "xsd:string",
                  "status_codes": "xsd:string",
                  "error_handling": "xsd:string",
                  "documentation_url": "xsd:anyURI",
                  "swagger_spec": "xsd:string",
                  "request_validation": "xsd:boolean",
                  "response_caching": "xsd:boolean",
                  "compression_enabled": "xsd:boolean",
                  "ssl_required": "xsd:boolean",
                  "cors_enabled": "xsd:boolean",
                  "webhook_support": "xsd:boolean",
                  "batch_operations": "xsd:boolean",
                  "pagination_support": "xsd:boolean",
                  "filtering_support": "xsd:boolean",
                  "sorting_support": "xsd:boolean",
                  "field_selection": "xsd:boolean",
                  "response_time_ms": "xsd:float",
                  "availability_percentage": "xsd:float",
                  "daily_requests": "xsd:integer",
                  "error_rate": "xsd:float",
                  "monitoring_enabled": "xsd:boolean",
                  "logging_level": "xsd:string",
                  "analytics_tracking": "xsd:boolean"
                }
              }
            }
          }
        }
      },

      "Digital_Communication_Platforms": {
        "collections": {
          "Messaging_Systems": {
            "entities": {
              "MessagingPlatform": {
                "properties": {
                  "platform_id": "xsd:string",
                  "platform_name": "xsd:string",
                  "platform_type": "xsd:string",
                  "service_provider": "xsd:string",
                  "launch_date": "xsd:date",
                  "user_base": "xsd:integer",
                  "active_users_daily": "xsd:integer",
                  "active_users_monthly": "xsd:integer",
                  "messages_per_day": "xsd:integer",
                  "supported_platforms": "xsd:string",
                  "supported_devices": "xsd:string",
                  "message_types": "xsd:string",
                  "file_sharing": "xsd:boolean",
                  "voice_messages": "xsd:boolean",
                  "video_messages": "xsd:boolean",
                  "group_messaging": "xsd:boolean",
                  "broadcast_messaging": "xsd:boolean",
                  "end_to_end_encryption": "xsd:boolean",
                  "message_retention": "xsd:string",
                  "read_receipts": "xsd:boolean",
                  "typing_indicators": "xsd:boolean",
                  "presence_status": "xsd:boolean",
                  "message_search": "xsd:boolean",
                  "message_backup": "xsd:boolean",
                  "cross_platform_sync": "xsd:boolean",
                  "api_integration": "xsd:boolean",
                  "bot_support": "xsd:boolean",
                  "business_features": "xsd:string",
                  "monetization_model": "xsd:string",
                  "privacy_policy": "xsd:string",
                  "data_retention_policy": "xsd:string",
                  "compliance_standards": "xsd:string"
                }
              },
              "Message": {
                "properties": {
                  "message_id": "xsd:string",
                  "conversation_id": "xsd:string",
                  "thread_id": "xsd:string",
                  "sender_id": "xsd:string",
                  "recipient_ids": "xsd:string",
                  "message_type": "xsd:string",
                  "content_type": "xsd:string",
                  "text_content": "xsd:string",
                  "media_attachments": "xsd:string",
                  "file_attachments": "xsd:string",
                  "location_data": "geo:Point",
                  "timestamp_sent": "xsd:dateTime",
                  "timestamp_delivered": "xsd:dateTime",
                  "timestamp_read": "xsd:dateTime",
                  "delivery_status": "xsd:string",
                  "read_status": "xsd:boolean",
                  "encryption_status": "xsd:boolean",
                  "priority_level": "xsd:string",
                  "expiration_time": "xsd:dateTime",
                  "reply_to_message": "xsd:string",
                  "forwarded_from": "xsd:string",
                  "edit_history": "xsd:string",
                  "reaction_count": "xsd:integer",
                  "reactions": "xsd:string",
                  "mentions": "xsd:string",
                  "hashtags": "xsd:string",
                  "links": "xsd:string",
                  "language": "xsd:string",
                  "sentiment_score": "xsd:float",
                  "spam_score": "xsd:float",
                  "content_moderation": "xsd:string",
                  "metadata": "xsd:string",
                  "client_info": "xsd:string",
                  "network_info": "xsd:string"
                }
              },
              "EmailSystem": {
                "properties": {
                  "email_system_id": "xsd:string",
                  "system_name": "xsd:string",
                  "provider": "xsd:string",
                  "deployment_type": "xsd:string",
                  "server_configuration": "xsd:string",
                  "supported_protocols": "xsd:string",
                  "security_features": "xsd:string",
                  "spam_filtering": "xsd:boolean",
                  "virus_scanning": "xsd:boolean",
                  "encryption_support": "xsd:string",
                  "digital_signatures": "xsd:boolean",
                  "mailbox_quota_gb": "xsd:float",
                  "attachment_size_limit_mb": "xsd:float",
                  "retention_policy": "xsd:string",
                  "backup_strategy": "xsd:string",
                  "disaster_recovery": "xsd:string",
                  "compliance_features": "xsd:string",
                  "audit_logging": "xsd:boolean",
                  "mobile_support": "xsd:boolean",
                  "offline_access": "xsd:boolean",
                  "calendar_integration": "xsd:boolean",
                  "contact_management": "xsd:boolean",
                  "task_management": "xsd:boolean",
                  "collaboration_features": "xsd:string",
                  "api_access": "xsd:boolean",
                  "third_party_integrations": "xsd:string",
                  "user_count": "xsd:integer",
                  "daily_volume": "xsd:integer",
                  "storage_used_gb": "xsd:float",
                  "uptime_percentage": "xsd:float"
                }
              }
            }
          },
          "Social_Media_Platforms": {
            "entities": {
              "SocialNetwork": {
                "properties": {
                  "network_id": "xsd:string",
                  "network_name": "xsd:string",
                  "platform_type": "xsd:string",
                  "target_audience": "xsd:string",
                  "primary_purpose": "xsd:string",
                  "content_focus": "xsd:string",
                  "user_demographics": "xsd:string",
                  "global_users": "xsd:integer",
                  "daily_active_users": "xsd:integer",
                  "monthly_active_users": "xsd:integer",
                  "user_growth_rate": "xsd:float",
                  "engagement_rate": "xsd:float",
                  "session_duration_minutes": "xsd:float",
                  "posts_per_day": "xsd:integer",
                  "content_types": "xsd:string",
                  "media_support": "xsd:string",
                  "live_streaming": "xsd:boolean",
                  "stories_feature": "xsd:boolean",
                  "direct_messaging": "xsd:boolean",
                  "group_features": "xsd:boolean",
                  "event_features": "xsd:boolean",
                  "marketplace": "xsd:boolean",
                  "advertising_platform": "xsd:boolean",
                  "creator_monetization": "xsd:boolean",
                  "content_moderation": "xsd:string",
                  "privacy_controls": "xsd:string",
                  "data_portability": "xsd:boolean",
                  "api_availability": "xsd:boolean",
                  "third_party_apps": "xsd:boolean",
                  "algorithm_transparency": "xsd:string",
                  "fact_checking": "xsd:boolean",
                  "misinformation_policies": "xsd:string"
                }
              },
              "SocialPost": {
                "properties": {
                  "post_id": "xsd:string",
                  "platform": "xsd:string",
                  "author_id": "xsd:string",
                  "author_handle": "xsd:string",
                  "author_verified": "xsd:boolean",
                  "post_type": "xsd:string",
                  "content_format": "xsd:string",
                  "text_content": "xsd:string",
                  "character_count": "xsd:integer",
                  "media_count": "xsd:integer",
                  "media_types": "xsd:string",
                  "media_urls": "xsd:string",
                  "hashtags": "xsd:string",
                  "mentions": "xsd:string",
                  "links": "xsd:string",
                  "location": "geo:Point",
                  "timestamp_created": "xsd:dateTime",
                  "timestamp_published": "xsd:dateTime",
                  "visibility": "xsd:string",
                  "audience": "xsd:string",
                  "language": "xsd:string",
                  "likes_count": "xsd:integer",
                  "shares_count": "xsd:integer",
                  "comments_count": "xsd:integer",
                  "views_count": "xsd:integer",
                  "reach": "xsd:integer",
                  "impressions": "xsd:integer",
                  "engagement_rate": "xsd:float",
                  "click_through_rate": "xsd:float",
                  "sentiment_score": "xsd:float",
                  "virality_score": "xsd:float",
                  "trending_status": "xsd:boolean",
                  "content_warnings": "xsd:string",
                  "age_restrictions": "xsd:string",
                  "monetization_enabled": "xsd:boolean",
                  "sponsored_content": "xsd:boolean",
                  "fact_checked": "xsd:boolean",
                  "content_moderation_flags": "xsd:string"
                }
              },
              "InfluencerProfile": {
                "properties": {
                  "influencer_id": "xsd:string",
                  "username": "xsd:string",
                  "display_name": "xsd:string",
                  "verified_status": "xsd:boolean",
                  "follower_count": "xsd:integer",
                  "following_count": "xsd:integer",
                  "post_count": "xsd:integer",
                  "engagement_rate": "xsd:float",
                  "average_likes": "xsd:float",
                  "average_comments": "xsd:float",
                  "average_shares": "xsd:float",
                  "reach_percentage": "xsd:float",
                  "audience_demographics": "xsd:string",
                  "audience_geography": "xsd:string",
                  "audience_interests": "xsd:string",
                  "content_categories": "xsd:string",
                  "posting_frequency": "xsd:string",
                  "optimal_posting_times": "xsd:string",
                  "brand_partnerships": "xsd:string",
                  "sponsored_post_rate": "xsd:float",
                  "collaboration_history": "xsd:string",
                  "authenticity_score": "xsd:float",
                  "fake_follower_percentage": "xsd:float",
                  "growth_rate": "xsd:float",
                  "influence_score": "xsd:float",
                  "niche_authority": "xsd:string",
                  "cross_platform_presence": "xsd:string",
                  "contact_information": "xsd:string",
                  "media_kit_url": "xsd:anyURI"
                }
              }
            }
          }
        }
      },

      "Broadcasting_Media": {
        "collections": {
          "Traditional_Media": {
            "entities": {
              "BroadcastStation": {
                "properties": {
                  "station_id": "xsd:string",
                  "call_sign": "xsd:string",
                  "station_name": "xsd:string",
                  "media_type": "xsd:string",
                  "broadcast_standard": "xsd:string",
                  "frequency": "xsd:float",
                  "channel_number": "xsd:string",
                  "transmitter_power": "xsd:float",
                  "coverage_area": "geo:Polygon",
                  "service_area": "xsd:string",
                  "population_served": "xsd:integer",
                  "market_rank": "xsd:integer",
                  "license_holder": "xsd:string",
                  "network_affiliation": "xsd:string",
                  "programming_format": "xsd:string",
                  "target_demographic": "xsd:string",
                  "broadcast_hours": "xsd:string",
                  "news_programming": "xsd:boolean",
                  "local_content_percentage": "xsd:float",
                  "syndicated_content": "xsd:string",
                  "advertising_revenue": "xsd:float",
                  "audience_ratings": "xsd:float",
                  "market_share": "xsd:float",
                  "digital_presence": "xsd:string",
                  "streaming_service": "xsd:boolean",
                  "podcast_offerings": "xsd:boolean",
                  "social_media_integration": "xsd:boolean",
                  "mobile_app": "xsd:boolean",
                  "emergency_alert_system": "xsd:boolean",
                  "accessibility_features": "xsd:string",
                  "regulatory_compliance": "xsd:string",
                  "license_expiration": "xsd:date"
                }
              },
              "TelevisionProgram": {
                "properties": {
                  "program_id": "xsd:string",
                  "program_title": "xsd:string",
                  "series_title": "xsd:string",
                  "episode_number": "xsd:integer",
                  "season_number": "xsd:integer",
                  "program_type": "xsd:string",
                  "genre": "xsd:string",
                  "subgenre": "xsd:string",
                  "target_audience": "xsd:string",
                  "age_rating": "xsd:string",
                  "content_warnings": "xsd:string",
                  "duration_minutes": "xsd:integer",
                  "production_year": "xsd:integer",
                  "production_company": "xsd:string",
                  "distributor": "xsd:string",
                  "director": "xsd:string",
                  "producer": "xsd:string",
                  "cast": "xsd:string",
                  "crew": "xsd:string",
                  "filming_locations": "xsd:string",
                  "production_budget": "xsd:float",
                  "original_air_date": "xsd:date",
                  "broadcast_network": "xsd:string",
                  "time_slot": "xsd:string",
                  "viewer_ratings": "xsd:float",
                  "audience_share": "xsd:float",
                  "critical_reception": "xsd:string",
                  "awards": "xsd:string",
                  "syndication_rights": "xsd:string",
                  "international_distribution": "xsd:string",
                  "streaming_availability": "xsd:string",
                  "merchandising": "xsd:string",
                  "social_media_buzz": "xsd:float",
                  "cultural_impact": "xsd:string"
                }
              },
              "RadioShow": {
                "properties": {
                  "show_id": "xsd:string",
                  "show_title": "xsd:string",
                  "show_format": "xsd:string",
                  "genre": "xsd:string",
                  "host": "xsd:string",
                  "co_hosts": "xsd:string",
                  "producer": "xsd:string",
                  "broadcast_schedule": "xsd:string",
                  "duration_minutes": "xsd:integer",
                  "target_demographic": "xsd:string",
                  "content_description": "xsd:string",
                  "music_format": "xsd:string",
                  "talk_segments": "xsd:boolean",
                  "news_segments": "xsd:boolean",
                  "weather_updates": "xsd:boolean",
                  "traffic_reports": "xsd:boolean",
                  "call_in_segments": "xsd:boolean",
                  "guest_interviews": "xsd:boolean",
                  "live_music": "xsd:boolean",
                  "contests_promotions": "xsd:boolean",
                  "listener_interaction": "xsd:string",
                  "social_media_integration": "xsd:boolean",
                  "podcast_version": "xsd:boolean",
                  "streaming_availability": "xsd:boolean",
                  "audience_size": "xsd:integer",
                  "listener_demographics": "xsd:string",
                  "ratings": "xsd:float",
                  "advertising_slots": "xsd:integer",
                  "sponsorship_deals": "xsd:string",
                  "community_involvement": "xsd:string"
                }
              }
            }
          },
          "Digital_Streaming": {
            "entities": {
              "StreamingPlatform": {
                "properties": {
                  "platform_id": "xsd:string",
                  "platform_name": "xsd:string",
                  "service_type": "xsd:string",
                  "content_focus": "xsd:string",
                  "launch_date": "xsd:date",
                  "global_availability": "xsd:boolean",
                  "supported_regions": "xsd:string",
                  "subscriber_count": "xsd:integer",
                  "free_tier": "xsd:boolean",
                  "premium_tiers": "xsd:string",
                  "pricing_model": "xsd:string",
                  "content_library_size": "xsd:integer",
                  "original_content": "xsd:boolean",
                  "licensed_content": "xsd:boolean",
                  "live_streaming": "xsd:boolean",
                  "offline_viewing": "xsd:boolean",
                  "simultaneous_streams": "xsd:integer",
                  "video_quality": "xsd:string",
                  "audio_quality": "xsd:string",
                  "subtitle_support": "xsd:boolean",
                  "dubbing_support": "xsd:boolean",
                  "accessibility_features": "xsd:string",
                  "parental_controls": "xsd:boolean",
                  "recommendation_engine": "xsd:boolean",
                  "user_profiles": "xsd:integer",
                  "watchlist_feature": "xsd:boolean",
                  "download_feature": "xsd:boolean",
                  "cross_device_sync": "xsd:boolean",
                  "supported_devices": "xsd:string",
                  "api_integration": "xsd:boolean",
                  "content_discovery": "xsd:string",
                  "social_features": "xsd:string"
                }
              },
              "LiveStream": {
                "properties": {
                  "stream_id": "xsd:string",
                  "stream_title": "xsd:string",
                  "streamer_id": "xsd:string",
                  "platform": "xsd:string",
                  "category": "xsd:string",
                  "tags": "xsd:string",
                  "start_time": "xsd:dateTime",
                  "end_time": "xsd:dateTime",
                  "duration_minutes": "xsd:integer",
                  "peak_viewers": "xsd:integer",
                  "average_viewers": "xsd:integer",
                  "total_views": "xsd:integer",
                  "unique_viewers": "xsd:integer",
                  "chat_messages": "xsd:integer",
                  "follower_gain": "xsd:integer",
                  "subscriber_gain": "xsd:integer",
                  "donations_received": "xsd:float",
                  "bits_cheered": "xsd:integer",
                  "video_quality": "xsd:string",
                  "audio_quality": "xsd:string",
                  "frame_rate": "xsd:integer",
                  "bitrate": "xsd:integer",
                  "encoding_settings": "xsd:string",
                  "streaming_software": "xsd:string",
                  "hardware_setup": "xsd:string",
                  "internet_speed": "xsd:float",
                  "stream_health": "xsd:string",
                  "dropped_frames": "xsd:integer",
                  "latency_ms": "xsd:float",
                  "chat_moderation": "xsd:boolean",
                  "subscriber_only_mode": "xsd:boolean",
                  "mature_content": "xsd:boolean",
                  "vod_available": "xsd:boolean"
                }
              }
            }
          }
        }
      },

      "Content_Management": {
        "collections": {
          "Digital_Content": {
            "entities": {
              "ContentItem": {
                "properties": {
                  "content_id": "xsd:string",
                  "title": "xsd:string",
                  "content_type": "xsd:string",
                  "format": "xsd:string",
                  "mime_type": "xsd:string",
                  "file_size_bytes": "xsd:integer",
                  "duration_seconds": "xsd:float",
                  "resolution": "xsd:string",
                  "aspect_ratio": "xsd:string",
                  "frame_rate": "xsd:float",
                  "bit_rate": "xsd:integer",
                  "color_space": "xsd:string",
                  "audio_channels": "xsd:integer",
                  "sample_rate": "xsd:integer",
                  "language": "xsd:string",
                  "subtitles": "xsd:string",
                  "captions": "xsd:boolean",
                  "description": "xsd:string",
                  "keywords": "xsd:string",
                  "tags": "xsd:string",
                  "categories": "xsd:string",
                  "author": "xsd:string",
                  "creator": "xsd:string",
                  "publisher": "xsd:string",
                  "creation_date": "xsd:dateTime",
                  "publication_date": "xsd:dateTime",
                  "last_modified": "xsd:dateTime",
                  "copyright_holder": "xsd:string",
                  "license_type": "xsd:string",
                  "usage_rights": "xsd:string",
                  "distribution_rights": "xsd:string",
                  "geographic_restrictions": "xsd:string",
                  "age_rating": "xsd:string",
                  "content_warnings": "xsd:string",
                  "accessibility_features": "xsd:string",
                  "seo_metadata": "xsd:string",
                  "social_metadata": "xsd:string",
                  "analytics_tracking": "xsd:boolean"
                }
              },
              "ContentDistribution": {
                "properties": {
                  "distribution_id": "xsd:string",
                  "content_id": "xsd:string",
                  "distribution_channel": "xsd:string",
                  "platform": "xsd:string",
                  "publication_status": "xsd:string",
                  "scheduled_time": "xsd:dateTime",
                  "actual_time": "xsd:dateTime",
                  "target_audience": "xsd:string",
                  "geographic_targeting": "xsd:string",
                  "demographic_targeting": "xsd:string",
                  "behavioral_targeting": "xsd:string",
                  "distribution_format": "xsd:string",
                  "quality_settings": "xsd:string",
                  "cdn_configuration": "xsd:string",
                  "caching_strategy": "xsd:string",
                  "delivery_method": "xsd:string",
                  "bandwidth_allocation": "xsd:float",
                  "cost_per_delivery": "xsd:float",
                  "performance_metrics": "xsd:string",
                  "delivery_success_rate": "xsd:float",
                  "error_rate": "xsd:float",
                  "user_engagement": "xsd:string",
                  "conversion_metrics": "xsd:string",
                  "revenue_attribution": "xsd:float",
                  "compliance_status": "xsd:string",
                  "content_moderation": "xsd:string",
                  "feedback_collection": "xsd:boolean",
                  "analytics_integration": "xsd:boolean"
                }
              }
            }
          }
        }
      },

      "Communication_Analytics": {
        "collections": {
          "Performance_Metrics": {
            "entities": {
              "CommunicationMetrics": {
                "properties": {
                  "metric_id": "xsd:string",
                  "metric_name": "xsd:string",
                  "metric_category": "xsd:string",
                  "measurement_period": "xsd:string",
                  "start_date": "xsd:date",
                  "end_date": "xsd:date",
                  "platform": "xsd:string",
                  "channel": "xsd:string",
                  "campaign_id": "xsd:string",
                  "content_id": "xsd:string",
                  "impressions": "xsd:integer",
                  "reach": "xsd:integer",
                  "unique_reach": "xsd:integer",
                  "frequency": "xsd:float",
                  "engagement_count": "xsd:integer",
                  "engagement_rate": "xsd:float",
                  "click_count": "xsd:integer",
                  "click_through_rate": "xsd:float",
                  "conversion_count": "xsd:integer",
                  "conversion_rate": "xsd:float",
                  "bounce_rate": "xsd:float",
                  "time_spent_seconds": "xsd:float",
                  "page_views": "xsd:integer",
                  "session_count": "xsd:integer",
                  "new_users": "xsd:integer",
                  "returning_users": "xsd:integer",
                  "user_retention_rate": "xsd:float",
                  "churn_rate": "xsd:float",
                  "sentiment_score": "xsd:float",
                  "brand_mention_count": "xsd:integer",
                  "share_of_voice": "xsd:float",
                  "virality_coefficient": "xsd:float",
                  "cost_per_impression": "xsd:float",
                  "cost_per_click": "xsd:float",
                  "cost_per_acquisition": "xsd:float",
                  "return_on_ad_spend": "xsd:float",
                  "lifetime_value": "xsd:float"
                }
              }
            }
          }
        }
      }
    },

    "relations": {
      "OPERATES_NETWORK": {"domain": "TelecomNetwork", "range": "BaseStation"},
      "HOSTS_IN_DATACENTER": {"domain": "DataCenter", "range": "ITSystem"},
      "USES_PROTOCOL": {"domain": "MessagingPlatform", "range": "NetworkProtocol"},
      "EXPOSES_API": {"domain": "MessagingPlatform", "range": "APIEndpoint"},
      "SENDS_MESSAGE": {"domain": "User", "range": "Message"},
      "RECEIVES_MESSAGE": {"domain": "User", "range": "Message"},
      "TRANSMITTED_VIA": {"domain": "Message", "range": "MessagingPlatform"},
      "POSTS_ON": {"domain": "User", "range": "SocialNetwork"},
      "CREATES_POST": {"domain": "User", "range": "SocialPost"},
      "PUBLISHED_ON": {"domain": "SocialPost", "range": "SocialNetwork"},
      "INFLUENCES_ON": {"domain": "InfluencerProfile", "range": "SocialNetwork"},
      "BROADCASTS_ON": {"domain": "BroadcastStation", "range": "TelevisionProgram"},
      "AIRS_ON": {"domain": "TelevisionProgram", "range": "BroadcastStation"},
      "HOSTS_SHOW": {"domain": "BroadcastStation", "range": "RadioShow"},
      "STREAMS_ON": {"domain": "StreamingPlatform", "range": "LiveStream"},
      "CREATES_STREAM": {"domain": "User", "range": "LiveStream"},
      "MANAGES_CONTENT": {"domain": "ContentItem", "range": "ContentDistribution"},
      "DISTRIBUTES_VIA": {"domain": "ContentDistribution", "range": "Platform"},
      "MEASURES_PERFORMANCE": {"domain": "CommunicationMetrics", "range": "Platform"},
      "TRACKS_CONTENT": {"domain": "CommunicationMetrics", "range": "ContentItem"},
      "ANALYZES_CAMPAIGN": {"domain": "CommunicationMetrics", "range": "Campaign"}
    }
  }
}